setup.py
distributions_lalitgsk/Binomialdistribution.py
distributions_lalitgsk/Gaussiandistribution.py
distributions_lalitgsk/Generaldistribution.py
distributions_lalitgsk/__init__.py
distributions_lalitgsk.egg-info/PKG-INFO
distributions_lalitgsk.egg-info/SOURCES.txt
distributions_lalitgsk.egg-info/dependency_links.txt
distributions_lalitgsk.egg-info/not-zip-safe
distributions_lalitgsk.egg-info/top_level.txt